Metadata-Version: 2.1
Name: hello-world-example
Version: 0.1.1
Summary: A hello-world example package
Home-page: https://github.com/mulkong/package_tutorial.git
Author: waterbottel2487
Author-email: waterbottle2487@gmail.com
Classifier: Programming Language :: Python :: 3
Classifier: License :: OSI Approved :: MIT License
Classifier: Operating System :: OS Independent
